postgresql_interface/__init__.py
postgresql_interface/custom_errors.py
postgresql_interface/postgresql_interface.py
postgresql_interface/sql_injection_bodyguard.py
postgresql_interface/sql_writer.py
postgresql_interface-1.0.2.dist-info/LICENSE.txt
postgresql_interface-1.0.2.dist-info/METADATA
postgresql_interface-1.0.2.dist-info/WHEEL
postgresql_interface-1.0.2.dist-info/top_level.txt
postgresql_interface-1.0.2.dist-info/RECORD
