Metadata-Version: 2.1
Name: postgresql-interface
Version: 1.0.2
Summary: Library to load and extract data from a PosgreSQL Database with Python with a simple SQL style language
Home-page: https://github.com/antjes88/PostgreSQLInterface
Author: Antonio Benjumea
License: MIT
Platform: UNKNOWN
Requires-Dist: numpy (==1.23.1)
Requires-Dist: pandas (==1.1.5)
Requires-Dist: psycopg2-binary (==2.8.5)
